basepkg/__init__.py
basepkg-0.2.0.dist-info/WHEEL
basepkg-0.2.0.dist-info/METADATA
basepkg-0.2.0.dist-info/RECORD
